biosimulators_cobrapy/__init__.py
biosimulators_cobrapy/__main__.py
biosimulators_cobrapy/_version.py
biosimulators_cobrapy/core.py
biosimulators_cobrapy/data_model.py
biosimulators_cobrapy/utils.py
biosimulators_cobrapy-0.1.23.dist-info/LICENSE
biosimulators_cobrapy-0.1.23.dist-info/METADATA
biosimulators_cobrapy-0.1.23.dist-info/WHEEL
biosimulators_cobrapy-0.1.23.dist-info/entry_points.txt
biosimulators_cobrapy-0.1.23.dist-info/top_level.txt
biosimulators_cobrapy-0.1.23.dist-info/RECORD
