Metadata-Version: 2.1
Name: biosimulators-cobrapy
Version: 0.1.23
Summary: BioSimulators-compliant command-line interface to the COBRApy simulation program <https://opencobra.github.io/cobrapy/>.
Home-page: https://github.com/biosimulators/biosimulators_cobrapy
Download-URL: https://github.com/biosimulators/biosimulators_cobrapy
Author: Center for Reproducible Biomedical Modeling
Author-email: info@biosimulators.org
License: MIT
Keywords: systems biology modeling simulation
Platform: UNKNOWN
Classifier: Development Status :: 3 - Alpha
Classifier: Intended Audience :: Science/Research
Classifier: License :: OSI Approved :: MIT License
Classifier: Topic :: Scientific/Engineering :: Bio-Informatics
License-File: LICENSE
Requires-Dist: biosimulators-utils[logging] (>=0.1.162)
Requires-Dist: cobra
Requires-Dist: kisao
Requires-Dist: lxml
Requires-Dist: numpy
Requires-Dist: python-libsbml
Provides-Extra: all
Requires-Dist: attrdict ; extra == 'all'
Requires-Dist: biosimulators-utils[containers] ; extra == 'all'
Requires-Dist: gurobipy ; extra == 'all'
Requires-Dist: python-dateutil ; extra == 'all'
Provides-Extra: docs
Provides-Extra: gurobi
Requires-Dist: gurobipy ; extra == 'gurobi'
Provides-Extra: tests
Requires-Dist: attrdict ; extra == 'tests'
Requires-Dist: biosimulators-utils[containers] ; extra == 'tests'
Requires-Dist: python-dateutil ; extra == 'tests'
